fortran_binary.py
fortran_binary-1.0.8.dist-info/LICENSE
fortran_binary-1.0.8.dist-info/METADATA
fortran_binary-1.0.8.dist-info/WHEEL
fortran_binary-1.0.8.dist-info/top_level.txt
fortran_binary-1.0.8.dist-info/RECORD
